DISAtool/DISAtool.py
DISAtool/__init__.py
DISAtool-1.0.1.dist-info/LICENSE
DISAtool-1.0.1.dist-info/METADATA
DISAtool-1.0.1.dist-info/WHEEL
DISAtool-1.0.1.dist-info/top_level.txt
DISAtool-1.0.1.dist-info/RECORD
