Metadata-Version: 2.1
Name: DISAtool
Version: 1.0.1
Summary: A library used to assess the informative and discriminative properties of subspaces/patterns
Home-page: https://github.com/JupitersMight/DISA
Author: L. Alexandre, R.S. Costa, R. Henriques
Author-email: leonardoalexandre@tecnico.ulisboa.pt
Project-URL: Bug Tracker, https://github.com/JupitersMight/DI2/issues
Keywords: multi-item discretization,prior-free discretization,heterogeneous biological data,data mining
Classifier: Programming Language :: Python :: 3
Classifier: License :: OSI Approved :: MIT License
Classifier: Operating System :: OS Independent
Requires-Python: >=3.7
License-File: LICENSE
Requires-Dist: scipy (==1.8.1)
Requires-Dist: prettytable
Requires-Dist: matplotlib
Requires-Dist: numpy
